xraybinaryorbit/__init__.py
xraybinaryorbit/main.py
xraybinaryorbit/fitting/__init__.py
xraybinaryorbit/fitting/fit_conic_orbit.py
xraybinaryorbit/fitting/fit_disc.py
xraybinaryorbit/fitting/fit_nh.py
xraybinaryorbit/fitting/fit_spiral.py
xraybinaryorbit/fitting/fit_spiral_orbit.py
xraybinaryorbit/helpers/__init__.py
xraybinaryorbit/helpers/data_helpers.py
xraybinaryorbit/helpers/math_helpers.py
xraybinaryorbit/theoretical/__init__.py
xraybinaryorbit/theoretical/density_related.py
xraybinaryorbit/theoretical/doppler_related.py
xraybinaryorbit/theoretical/orbital_velocity_related.py
xraybinaryorbit/timing/__init__.py
xraybinaryorbit/timing/timing_related.py
xraybinaryorbit-1.0.1.dist-info/LICENSE
xraybinaryorbit-1.0.1.dist-info/METADATA
xraybinaryorbit-1.0.1.dist-info/WHEEL
xraybinaryorbit-1.0.1.dist-info/top_level.txt
xraybinaryorbit-1.0.1.dist-info/RECORD
